MANIFEST.in
README.md
VERSION
requirements.txt
setup.cfg
setup.py
bundletester/__init__.py
bundletester/builder.py
bundletester/config.py
bundletester/fetchers.py
bundletester/models.py
bundletester/reporter.py
bundletester/runner.py
bundletester/spec.py
bundletester/tester.py
bundletester/utils.py
bundletester/watcher.py
bundletester.egg-info/PKG-INFO
bundletester.egg-info/SOURCES.txt
bundletester.egg-info/dependency_links.txt
bundletester.egg-info/entry_points.txt
bundletester.egg-info/pbr.json
bundletester.egg-info/requires.txt
bundletester.egg-info/top_level.txt