Metadata-Version: 1.0
Name: bundletester
Version: 0.12.0
Summary: A juju charm and bundle test runner
Home-page: https://github.com/juju-solutions/bundletester
Author: Juju Developers
Author-email: juju@lists.ubuntu.com
License: Affero GNU Public License v3
Platform: UNKNOWN
